isoplot/__init__.py
isoplot/logger.py
isoplot/main/__init__.py
isoplot/main/cli_process.py
isoplot/main/dataprep.py
isoplot/main/plots.py
isoplot/tests/__init__.py
isoplot/tests/test_dataprep.py
isoplot/ui/__init__.py
isoplot/ui/isoplot_notebook.py
isoplot/ui/isoplotcli.py
isoplot/ui/object_notebook.py
isoplot-1.3.1.dist-info/LICENSE.txt
isoplot-1.3.1.dist-info/METADATA
isoplot-1.3.1.dist-info/WHEEL
isoplot-1.3.1.dist-info/entry_points.txt
isoplot-1.3.1.dist-info/top_level.txt
isoplot-1.3.1.dist-info/RECORD
