Metadata-Version: 2.1
Name: isoplot
Version: 1.3.1
Summary: Generate figures from Isocor output
Home-page: https://github.com/LoloPopoPy/Isoplot
Author: Loïc Le Grégam
Author-email: loic.le-gregam@insa-toulouse.fr
License: UNKNOWN
Platform: UNKNOWN
Classifier: Development Status :: 4 - Beta
Classifier: License :: OSI Approved :: GNU General Public License v3 (GPLv3)
Classifier: Natural Language :: French
Classifier: Operating System :: OS Independent
Classifier: Programming Language :: Python :: 3.6
Classifier: Programming Language :: Python :: 3.7
Classifier: Programming Language :: Python :: 3.8
Classifier: Programming Language :: Python :: 3.9
Classifier: Topic :: Scientific/Engineering :: Bio-Informatics
Requires-Dist: numpy (>=1.19.1)
Requires-Dist: pandas (>=1.1.1)
Requires-Dist: matplotlib (>=3.3.1)
Requires-Dist: seaborn (>=0.10.1)
Requires-Dist: natsort (>=7.0.1)
Requires-Dist: bokeh (==2.0.2)
Requires-Dist: ipywidgets (>=7.5.1)
Requires-Dist: colorcet (>=2.0.2)
Requires-Dist: openpyxl (>=3.0.5)
Requires-Dist: xlrd (>=1.2.0)
Provides-Extra: dev
Requires-Dist: Sphinx ; extra == 'dev'
Requires-Dist: sphinx-argparse ; extra == 'dev'
Requires-Dist: autodoc ; extra == 'dev'
Requires-Dist: sphinx-rtd-theme ; extra == 'dev'
Requires-Dist: sdist ; extra == 'dev'
Requires-Dist: twine ; extra == 'dev'
Requires-Dist: pytest ; extra == 'dev'
